classitransformers/__init__.py
classitransformers/configs.py
classitransformers/downloader.py
classitransformers/pytransformers.py
classitransformers/report.py
classitransformers/tfbert.py
classitransformers/tfelectra.py
electra/__init__.py
electra/modeling.py
electra/optimization.py
electra/tokenization.py
classitransformers-0.0.1.dist-info/LICENSE.md
classitransformers-0.0.1.dist-info/METADATA
classitransformers-0.0.1.dist-info/NOTICES.txt
classitransformers-0.0.1.dist-info/WHEEL
classitransformers-0.0.1.dist-info/top_level.txt
classitransformers-0.0.1.dist-info/RECORD
