Metadata-Version: 2.1
Name: classitransformers
Version: 0.0.1
Summary: An abstract library for implementing text classification tasks based on various transformers based language models
Home-page: https://github.com/fidelity/classitransformers
Author: FMR LLC
Author-email: classitransformers@fmr.com
License: UNKNOWN
Project-URL: Source, https://github.com/fidelity/classitransformers
Keywords: NLP language_models text_classification bert electra roberta distilbert albert
Platform: UNKNOWN
Classifier: Programming Language :: Python :: 3.6
Classifier: License :: OSI Approved :: Apache Software License
Classifier: Operating System :: OS Independent
Requires-Python: >=3.6
Requires-Dist: tensorflow-gpu (==1.15.2)
Requires-Dist: bert-tensorflow
Requires-Dist: torch (==1.5.1)
Requires-Dist: torchvision (==0.6.1)
Requires-Dist: transformers (==2.11.0)
Requires-Dist: wget
